dirview/__init__.py
dirview/main.py
dirview-0.1.5.dist-info/METADATA
dirview-0.1.5.dist-info/WHEEL
dirview-0.1.5.dist-info/entry_points.txt
dirview-0.1.5.dist-info/top_level.txt
dirview-0.1.5.dist-info/RECORD
