Metadata-Version: 2.1
Name: dirview
Version: 0.1.5
Summary: A simple directory tree display tool
Author-email: 陈定钢 <945036663@qq.com>
Requires-Python: >=3.6
